[
  {
    "sourceResultId": "live3-weather-nairobi",
    "requestType": "weather",
    "providerName": "mock-weather-provider",
    "providerMode": "mock",
    "sourceName": "Mock Weather Provider",
    "sourceCategory": "weather",
    "sourceUrl": "provider:mock-weather",
    "query": "weather in Nairobi",
    "resultSummary": "Nairobi fixture weather: mild conditions with a chance of light rain.",
    "rawResultAvailable": false,
    "retrievedAt": "2026-06-28T12:00:00.000Z",
    "lastUpdated": "2026-06-28T11:45:00.000Z",
    "freshnessStatus": "recent",
    "confidenceLevel": "medium",
    "limitationNotes": "Mock weather result for contract validation only.",
    "evidenceStatus": "mock-backed",
    "sourceStatus": "source-result-available",
    "readOnly": true,
    "noExecutionRequired": true,
    "executionAuthority": false
  },
  {
    "sourceResultId": "live3-weather-kinshasa",
    "requestType": "weather",
    "providerName": "mock-weather-provider",
    "providerMode": "mock",
    "sourceName": "Mock Weather Provider",
    "sourceCategory": "weather",
    "sourceUrl": "provider:mock-weather",
    "query": "weather in Kinshasa",
    "resultSummary": "Kinshasa fixture weather: warm and humid with possible afternoon showers.",
    "rawResultAvailable": false,
    "retrievedAt": "2026-06-28T12:00:00.000Z",
    "lastUpdated": "2026-06-28T11:40:00.000Z",
    "freshnessStatus": "recent",
    "confidenceLevel": "medium",
    "limitationNotes": "Mock weather result for contract validation only.",
    "evidenceStatus": "mock-backed",
    "sourceStatus": "source-result-available",
    "readOnly": true,
    "noExecutionRequired": true,
    "executionAuthority": false
  },
  {
    "sourceResultId": "live3-security-eastern-drc",
    "requestType": "news-security",
    "providerName": "mock-security-provider",
    "providerMode": "mock",
    "sourceName": "Mock Security Source",
    "sourceCategory": "conflict-security",
    "sourceUrl": "provider:mock-security",
    "query": "security near eastern DRC and Goma",
    "resultSummary": "Fixture security context notes caution near eastern DRC and requires verified live sources before travel decisions.",
    "rawResultAvailable": false,
    "retrievedAt": "2026-06-28T12:00:00.000Z",
    "lastUpdated": "2026-06-28T10:30:00.000Z",
    "freshnessStatus": "recent",
    "confidenceLevel": "low",
    "limitationNotes": "Conflict/security answers require multiple current sources and must not be treated as travel clearance.",
    "evidenceStatus": "mock-backed",
    "sourceStatus": "source-result-available",
    "readOnly": true,
    "noExecutionRequired": true,
    "executionAuthority": false
  },
  {
    "sourceResultId": "live3-news-sudan",
    "requestType": "news-security",
    "providerName": "mock-news-provider",
    "providerMode": "mock",
    "sourceName": "Mock Current Events Source",
    "sourceCategory": "current-events",
    "sourceUrl": "provider:mock-news",
    "query": "current events Sudan",
    "resultSummary": "Sudan fixture current-events result requires live source verification before user-facing decisions.",
    "rawResultAvailable": false,
    "retrievedAt": "2026-06-28T12:00:00.000Z",
    "lastUpdated": "2026-06-28T09:00:00.000Z",
    "freshnessStatus": "recent",
    "confidenceLevel": "low",
    "limitationNotes": "Mock current-events source; no emergency or travel action is authorized.",
    "evidenceStatus": "mock-backed",
    "sourceStatus": "source-result-available",
    "readOnly": true,
    "noExecutionRequired": true,
    "executionAuthority": false
  },
  {
    "sourceResultId": "live3-shipment-in-transit",
    "requestType": "shipment-tracking",
    "providerName": "mock-shipment-provider",
    "providerMode": "mock",
    "sourceName": "Mock Shipment Provider",
    "sourceCategory": "shipment-tracking",
    "sourceUrl": "provider:mock-shipment",
    "query": "tracking [redacted-long-identifier]",
    "resultSummary": "Shipment fixture status: in transit means the parcel is moving through the carrier network.",
    "rawResultAvailable": false,
    "retrievedAt": "2026-06-28T12:00:00.000Z",
    "lastUpdated": "2026-06-28T08:00:00.000Z",
    "freshnessStatus": "recent",
    "confidenceLevel": "medium",
    "limitationNotes": "Tracking number is redacted; fixture does not change delivery instructions.",
    "evidenceStatus": "mock-backed",
    "sourceStatus": "source-result-available",
    "readOnly": true,
    "noExecutionRequired": true,
    "executionAuthority": false
  },
  {
    "sourceResultId": "live3-shipment-delivered",
    "requestType": "shipment-tracking",
    "providerName": "mock-shipment-provider",
    "providerMode": "mock",
    "sourceName": "Mock Shipment Provider",
    "sourceCategory": "shipment-tracking",
    "sourceUrl": "provider:mock-shipment",
    "query": "tracking [redacted-long-identifier]",
    "resultSummary": "Shipment fixture status: delivered. Confirm with the carrier before taking action.",
    "rawResultAvailable": false,
    "retrievedAt": "2026-06-28T12:00:00.000Z",
    "lastUpdated": "2026-06-27T18:00:00.000Z",
    "freshnessStatus": "recent",
    "confidenceLevel": "medium",
    "limitationNotes": "Fixture result only; no carrier contact or delivery change occurred.",
    "evidenceStatus": "mock-backed",
    "sourceStatus": "source-result-available",
    "readOnly": true,
    "noExecutionRequired": true,
    "executionAuthority": false
  },
  {
    "sourceResultId": "live3-shipment-provider-not-configured",
    "requestType": "shipment-tracking",
    "providerName": "AfterShip",
    "providerMode": "fixture",
    "sourceName": "AfterShip",
    "sourceCategory": "shipment-tracking",
    "sourceUrl": "provider-not-configured",
    "query": "track shipment",
    "resultSummary": "Shipment provider is not configured. Nexus needs a provider connection before live tracking.",
    "rawResultAvailable": false,
    "retrievedAt": "2026-06-28T12:00:00.000Z",
    "lastUpdated": "2026-06-28T12:00:00.000Z",
    "freshnessStatus": "unavailable",
    "confidenceLevel": "low",
    "limitationNotes": "No live tracking lookup occurred.",
    "evidenceStatus": "source-unavailable",
    "sourceStatus": "provider-not-configured",
    "readOnly": true,
    "noExecutionRequired": true,
    "executionAuthority": false
  },
  {
    "sourceResultId": "live3-agriculture-market-weather",
    "requestType": "agriculture-context",
    "providerName": "mock-agriculture-context-provider",
    "providerMode": "mock",
    "sourceName": "Mock Agriculture Context Source",
    "sourceCategory": "agriculture-context",
    "sourceUrl": "provider:mock-agriculture",
    "query": "agriculture weather and market context",
    "resultSummary": "Fixture agriculture context combines weather caution and market context without purchase or sale authority.",
    "rawResultAvailable": false,
    "retrievedAt": "2026-06-28T12:00:00.000Z",
    "lastUpdated": "2026-06-28T07:30:00.000Z",
    "freshnessStatus": "recent",
    "confidenceLevel": "medium",
    "limitationNotes": "Mock agriculture context only; verify with public or partner sources before decisions.",
    "evidenceStatus": "mock-backed",
    "sourceStatus": "source-result-available",
    "readOnly": true,
    "noExecutionRequired": true,
    "executionAuthority": false
  },
  {
    "sourceResultId": "live3-music-rnb-provider-not-connected",
    "requestType": "music-media",
    "providerName": "Spotify",
    "providerMode": "fixture",
    "sourceName": "Spotify",
    "sourceCategory": "music-media",
    "sourceUrl": "provider-not-connected",
    "query": "play R&B music",
    "resultSummary": "Music provider is not connected. Nexus can prepare provider options but will not play or stream music.",
    "rawResultAvailable": false,
    "retrievedAt": "2026-06-28T12:00:00.000Z",
    "lastUpdated": "2026-06-28T12:00:00.000Z",
    "freshnessStatus": "unavailable",
    "confidenceLevel": "low",
    "limitationNotes": "No account authentication, playlist creation, or streaming occurred.",
    "evidenceStatus": "source-unavailable",
    "sourceStatus": "provider-not-connected",
    "readOnly": true,
    "noExecutionRequired": true,
    "executionAuthority": false
  },
  {
    "sourceResultId": "live3-stale-weather-source",
    "requestType": "weather",
    "providerName": "mock-weather-provider",
    "providerMode": "mock",
    "sourceName": "Mock Weather Provider",
    "sourceCategory": "weather",
    "sourceUrl": "provider:mock-weather",
    "query": "weather tomorrow",
    "resultSummary": "Weather fixture is stale and must be refreshed before current use.",
    "rawResultAvailable": false,
    "retrievedAt": "2026-06-28T12:00:00.000Z",
    "lastUpdated": "2026-06-20T12:00:00.000Z",
    "freshnessStatus": "stale",
    "confidenceLevel": "low",
    "limitationNotes": "Stale fixture result; user-facing response must disclose stale data.",
    "evidenceStatus": "mock-backed",
    "sourceStatus": "source-stale",
    "readOnly": true,
    "noExecutionRequired": true,
    "executionAuthority": false
  },
  {
    "sourceResultId": "live3-conflicting-security-source",
    "requestType": "news-security",
    "providerName": "mock-security-provider",
    "providerMode": "mock",
    "sourceName": "Mock Security Source",
    "sourceCategory": "conflict-security",
    "sourceUrl": "provider:mock-security",
    "query": "security report conflict",
    "resultSummary": "Security fixture contains conflicting source signals and requires disclosure.",
    "rawResultAvailable": false,
    "retrievedAt": "2026-06-28T12:00:00.000Z",
    "lastUpdated": "2026-06-28T09:30:00.000Z",
    "freshnessStatus": "conflicting",
    "confidenceLevel": "low",
    "limitationNotes": "Source conflict detected; Nexus must not imply certainty.",
    "evidenceStatus": "conflicting",
    "sourceStatus": "source-conflict-detected",
    "readOnly": true,
    "noExecutionRequired": true,
    "executionAuthority": false
  },
  {
    "sourceResultId": "live3-provider-rate-limited",
    "requestType": "provider-status",
    "providerName": "mock-news-provider",
    "providerMode": "mock",
    "sourceName": "Mock News Provider",
    "sourceCategory": "provider-status",
    "sourceUrl": "provider:mock-news",
    "query": "provider status",
    "resultSummary": "Provider rate limit fixture: try again later or use another configured source.",
    "rawResultAvailable": false,
    "retrievedAt": "2026-06-28T12:00:00.000Z",
    "lastUpdated": "2026-06-28T12:00:00.000Z",
    "freshnessStatus": "unavailable",
    "confidenceLevel": "low",
    "limitationNotes": "Rate-limited source must not be treated as current data.",
    "evidenceStatus": "source-unavailable",
    "sourceStatus": "source-rate-limited",
    "readOnly": true,
    "noExecutionRequired": true,
    "executionAuthority": false
  },
  {
    "sourceResultId": "live3-provider-error",
    "requestType": "provider-status",
    "providerName": "mock-provider",
    "providerMode": "mock",
    "sourceName": "Mock Provider",
    "sourceCategory": "provider-status",
    "sourceUrl": "provider:mock",
    "query": "provider error",
    "resultSummary": "Provider error fixture: Nexus must disclose the error and avoid guessing.",
    "rawResultAvailable": false,
    "retrievedAt": "2026-06-28T12:00:00.000Z",
    "lastUpdated": "2026-06-28T12:00:00.000Z",
    "freshnessStatus": "unavailable",
    "confidenceLevel": "low",
    "limitationNotes": "Provider error; no live result available.",
    "evidenceStatus": "source-unavailable",
    "sourceStatus": "source-error",
    "readOnly": true,
    "noExecutionRequired": true,
    "executionAuthority": false
  },
  {
    "sourceResultId": "live3-unsupported-request-type",
    "requestType": "unsupported",
    "providerName": "mock-general-provider",
    "providerMode": "fixture",
    "sourceName": "Mock General Provider",
    "sourceCategory": "unsupported",
    "sourceUrl": "provider:mock-general",
    "query": "unsupported request",
    "resultSummary": "Unsupported request fixture: Nexus should ask for a supported source category.",
    "rawResultAvailable": false,
    "retrievedAt": "2026-06-28T12:00:00.000Z",
    "lastUpdated": "2026-06-28T12:00:00.000Z",
    "freshnessStatus": "unknown",
    "confidenceLevel": "unknown",
    "limitationNotes": "Unsupported request type; no lookup occurred.",
    "evidenceStatus": "not-source-backed",
    "sourceStatus": "unsupported",
    "readOnly": true,
    "noExecutionRequired": true,
    "executionAuthority": false
  },
  {
    "sourceResultId": "live3-job-kenya-farm",
    "requestType": "job-search",
    "providerName": "mock-job-provider",
    "providerMode": "mock",
    "sourceName": "Mock Job Board",
    "sourceCategory": "job-search",
    "sourceUrl": "provider:mock-jobs",
    "query": "farm jobs near Nairobi",
    "resultSummary": "Fixture job result: Farm Operations Assistant near Nairobi.",
    "rawResultAvailable": false,
    "retrievedAt": "2026-06-28T12:00:00.000Z",
    "lastUpdated": "2026-06-28T06:00:00.000Z",
    "freshnessStatus": "recent",
    "confidenceLevel": "medium",
    "limitationNotes": "Mock job posting; application submission is disabled.",
    "evidenceStatus": "mock-backed",
    "sourceStatus": "source-result-available",
    "readOnly": true,
    "noExecutionRequired": true,
    "executionAuthority": false,
    "jobResultId": "job-kenya-farm-assistant",
    "jobTitle": "Farm Operations Assistant",
    "employerName": "Mock Nairobi Growers",
    "employerType": "agriculture",
    "jobLocation": "Nairobi area",
    "country": "Kenya",
    "cityOrRegion": "Nairobi",
    "remoteOrOnsite": "onsite",
    "employmentType": "full-time",
    "salaryOrCompensation": "not listed",
    "postedDate": "2026-06-27",
    "applicationDeadline": "not listed",
    "applicationUrl": "provider:mock-jobs/job-kenya-farm-assistant",
    "applicationActionAllowed": false,
    "applicationSubmissionAuthority": false
  },
  {
    "sourceResultId": "live3-job-ghana-electrical",
    "requestType": "job-search",
    "providerName": "mock-job-provider",
    "providerMode": "mock",
    "sourceName": "Mock Job Board",
    "sourceCategory": "job-search",
    "sourceUrl": "provider:mock-jobs",
    "query": "solar electrical technician jobs in Ghana",
    "resultSummary": "Fixture job result: Solar Electrical Technician in Ghana.",
    "rawResultAvailable": false,
    "retrievedAt": "2026-06-28T12:00:00.000Z",
    "lastUpdated": "2026-06-27T15:00:00.000Z",
    "freshnessStatus": "recent",
    "confidenceLevel": "medium",
    "limitationNotes": "Mock job posting; no employer contact or application submission occurred.",
    "evidenceStatus": "mock-backed",
    "sourceStatus": "source-result-available",
    "readOnly": true,
    "noExecutionRequired": true,
    "executionAuthority": false,
    "jobResultId": "job-ghana-solar-electrical",
    "jobTitle": "Solar Electrical Technician",
    "employerName": "Mock Solar Workforce Ghana",
    "employerType": "energy",
    "jobLocation": "Accra region",
    "country": "Ghana",
    "cityOrRegion": "Accra",
    "remoteOrOnsite": "onsite",
    "employmentType": "contract",
    "salaryOrCompensation": "not listed",
    "postedDate": "2026-06-27",
    "applicationDeadline": "not listed",
    "applicationUrl": "provider:mock-jobs/job-ghana-solar-electrical",
    "applicationActionAllowed": false,
    "applicationSubmissionAuthority": false
  },
  {
    "sourceResultId": "live3-job-stale-posting",
    "requestType": "job-search",
    "providerName": "mock-job-provider",
    "providerMode": "mock",
    "sourceName": "Mock Job Board",
    "sourceCategory": "job-search",
    "sourceUrl": "provider:mock-jobs",
    "query": "stale job posting",
    "resultSummary": "Fixture stale job posting requires freshness disclosure.",
    "rawResultAvailable": false,
    "retrievedAt": "2026-06-28T12:00:00.000Z",
    "lastUpdated": "2026-05-01T12:00:00.000Z",
    "freshnessStatus": "stale",
    "confidenceLevel": "low",
    "limitationNotes": "Job posting may be expired; do not claim it is open.",
    "evidenceStatus": "mock-backed",
    "sourceStatus": "source-stale",
    "readOnly": true,
    "noExecutionRequired": true,
    "executionAuthority": false,
    "jobResultId": "job-stale-posting",
    "jobTitle": "Expired Farm Role",
    "employerName": "Mock Employer",
    "employerType": "agriculture",
    "jobLocation": "unknown",
    "country": "Kenya",
    "cityOrRegion": "unknown",
    "remoteOrOnsite": "onsite",
    "employmentType": "unknown",
    "salaryOrCompensation": "not listed",
    "postedDate": "2026-05-01",
    "applicationDeadline": "unknown",
    "applicationUrl": "provider:mock-jobs/job-stale-posting",
    "applicationActionAllowed": false,
    "applicationSubmissionAuthority": false
  },
  {
    "sourceResultId": "live3-job-unverified-employer",
    "requestType": "job-search",
    "providerName": "mock-job-provider",
    "providerMode": "mock",
    "sourceName": "Mock Job Board",
    "sourceCategory": "job-search",
    "sourceUrl": "provider:mock-jobs",
    "query": "unverified employer job",
    "resultSummary": "Fixture job posting has an unverified employer and requires caution.",
    "rawResultAvailable": false,
    "retrievedAt": "2026-06-28T12:00:00.000Z",
    "lastUpdated": "2026-06-25T12:00:00.000Z",
    "freshnessStatus": "recent",
    "confidenceLevel": "low",
    "limitationNotes": "Employer is unverified; no application or contact is allowed.",
    "evidenceStatus": "mock-backed",
    "sourceStatus": "source-result-available",
    "readOnly": true,
    "noExecutionRequired": true,
    "executionAuthority": false,
    "jobResultId": "job-unverified-employer",
    "jobTitle": "Agriculture Sales Assistant",
    "employerName": "Unverified Mock Employer",
    "employerType": "unverified",
    "jobLocation": "Kampala",
    "country": "Uganda",
    "cityOrRegion": "Kampala",
    "remoteOrOnsite": "onsite",
    "employmentType": "unknown",
    "salaryOrCompensation": "not verified",
    "postedDate": "2026-06-25",
    "applicationDeadline": "not verified",
    "applicationUrl": "provider:mock-jobs/job-unverified-employer",
    "applicationActionAllowed": false,
    "applicationSubmissionAuthority": false
  },
  {
    "sourceResultId": "live3-job-application-prep-blocked",
    "requestType": "job-application-preparation",
    "providerName": "mock-job-provider",
    "providerMode": "mock",
    "sourceName": "Mock Job Application Prep",
    "sourceCategory": "job-application-preparation",
    "sourceUrl": "provider:mock-jobs/application-prep",
    "query": "help me apply for this job",
    "resultSummary": "Application preparation fixture: Nexus can draft a checklist, resume edits, and cover letter, but cannot submit.",
    "rawResultAvailable": false,
    "retrievedAt": "2026-06-28T12:00:00.000Z",
    "lastUpdated": "2026-06-28T12:00:00.000Z",
    "freshnessStatus": "recent",
    "confidenceLevel": "medium",
    "limitationNotes": "Application submission, employer contact, account login, resume upload, and email sending are blocked.",
    "evidenceStatus": "mock-backed",
    "sourceStatus": "source-result-available",
    "readOnly": true,
    "noExecutionRequired": true,
    "executionAuthority": false,
    "jobResultId": "job-application-prep-blocked",
    "jobTitle": "Selected mock role",
    "employerName": "Mock Employer",
    "employerType": "workforce",
    "jobLocation": "Kenya",
    "country": "Kenya",
    "cityOrRegion": "not specified",
    "remoteOrOnsite": "unknown",
    "employmentType": "unknown",
    "salaryOrCompensation": "not listed",
    "postedDate": "unknown",
    "applicationDeadline": "unknown",
    "applicationUrl": "provider:mock-jobs/application-prep",
    "applicationActionAllowed": false,
    "applicationSubmissionAuthority": false
  },
  {
    "sourceResultId": "live3-general-source-unavailable",
    "requestType": "general-question",
    "providerName": "mock-general-provider",
    "providerMode": "fixture",
    "sourceName": "General Source Required",
    "sourceCategory": "general-question",
    "sourceUrl": "provider-required",
    "query": "general question requiring current source",
    "resultSummary": "Nexus needs a verified source before answering this current factual question.",
    "rawResultAvailable": false,
    "retrievedAt": "2026-06-28T12:00:00.000Z",
    "lastUpdated": "2026-06-28T12:00:00.000Z",
    "freshnessStatus": "unavailable",
    "confidenceLevel": "low",
    "limitationNotes": "No live source is connected for this question; Nexus must not guess.",
    "evidenceStatus": "source-unavailable",
    "sourceStatus": "provider-required",
    "readOnly": true,
    "noExecutionRequired": true,
    "executionAuthority": false
  }
]
